LICENSE.txt
MANIFEST.in
README.md
setup.cfg
setup.py
copaco/__init__.py
copaco/connection.py
copaco/ftphandler.py
copaco/orders.py
copaco/utils.py
copaco/xmlhandler.py
copaco/constants/__init__.py
copaco/constants/constants.py
copaco/constants/errors.py
copaco/constants/mappings.py
copaco/models/__init__.py
copaco/models/base.py
copaco/models/order.py
copaco/models/pricelist.py
copaco/models/responses.py
copaco/temp/__init__.py
copaco/types/__init__.py
copaco/types/base.py
copaco/types/pricelist.py
python_copaco_connections.egg-info/PKG-INFO
python_copaco_connections.egg-info/SOURCES.txt
python_copaco_connections.egg-info/dependency_links.txt
python_copaco_connections.egg-info/requires.txt
python_copaco_connections.egg-info/top_level.txt