Metadata-Version: 2.1
Name: python-copaco-connections
Version: 1.0.0
Summary: Easy python integrations for the Copaco Customer Connections
Home-page: https://github.com/alexanderlhsglobal/python-copaco-connections
Author: Alexander Schillemans
Author-email: alexander.schillemans@lhs.global
License: GPL-3.0-or-later
Download-URL: https://github.com/alexanderlhsglobal/python-copaco-connections/archive/refs/tags/1.0.0.tar.gz
Keywords: copaco,api,customer connections
Platform: UNKNOWN
Classifier: Development Status :: 3 - Alpha
Classifier: Intended Audience :: Developers
Classifier: Topic :: Software Development :: Build Tools
Classifier: License :: OSI Approved :: GNU General Public License v3 or later (GPLv3+)
Classifier: Programming Language :: Python :: 3.6
License-File: LICENSE.txt
